<?xml version="1.0" encoding="UTF-8" standalone="no"?>
<villages>
  <village>
    <villageId>64000080001</villageId>
    <villageName>博仁里</villageName>
  </village>
  <village>
    <villageId>64000080002</villageId>
    <villageName>苓洲里</villageName>
  </village>
  <village>
    <villageId>64000080003</villageId>
    <villageName>苓昇里</villageName>
  </village>
  <village>
    <villageId>64000080004</villageId>
    <villageName>苓中里</villageName>
  </village>
  <village>
    <villageId>64000080005</villageId>
    <villageName>苓雅里</villageName>
  </village>
  <village>
    <villageId>64000080006</villageId>
    <villageName>苓東里</villageName>
  </village>
  <village>
    <villageId>64000080007</villageId>
    <villageName>城北里</villageName>
  </village>
  <village>
    <villageId>64000080008</villageId>
    <villageName>城西里</villageName>
  </village>
  <village>
    <villageId>64000080009</villageId>
    <villageName>城東里</villageName>
  </village>
  <village>
    <villageId>64000080010</villageId>
    <villageName>意誠里</villageName>
  </village>
  <village>
    <villageId>64000080011</villageId>
    <villageName>鼓中里</villageName>
  </village>
  <village>
    <villageId>64000080012</villageId>
    <villageName>田西里</villageName>
  </village>
  <village>
    <villageId>64000080013</villageId>
    <villageName>人和里</villageName>
  </village>
  <village>
    <villageId>64000080014</villageId>
    <villageName>仁政里</villageName>
  </village>
  <village>
    <villageId>64000080015</villageId>
    <villageName>廣澤里</villageName>
  </village>
  <village>
    <villageId>64000080016</villageId>
    <villageName>美田里</villageName>
  </village>
  <village>
    <villageId>64000080017</villageId>
    <villageName>華堂里</villageName>
  </village>
  <village>
    <villageId>64000080018</villageId>
    <villageName>日中里</villageName>
  </village>
  <village>
    <villageId>64000080019</villageId>
    <villageName>普照里</villageName>
  </village>
  <village>
    <villageId>64000080020</villageId>
    <villageName>和煦里</villageName>
  </village>
  <village>
    <villageId>64000080021</villageId>
    <villageName>晴朗里</villageName>
  </village>
  <village>
    <villageId>64000080022</villageId>
    <villageName>普天里</villageName>
  </village>
  <village>
    <villageId>64000080023</villageId>
    <villageName>林富里</villageName>
  </village>
  <village>
    <villageId>64000080024</villageId>
    <villageName>林圍里</villageName>
  </village>
  <village>
    <villageId>64000080025</villageId>
    <villageName>林安里</villageName>
  </village>
  <village>
    <villageId>64000080026</villageId>
    <villageName>光華里</villageName>
  </village>
  <village>
    <villageId>64000080027</villageId>
    <villageName>林興里</villageName>
  </village>
  <village>
    <villageId>64000080028</villageId>
    <villageName>林華里</villageName>
  </village>
  <village>
    <villageId>64000080029</villageId>
    <villageName>林西里</villageName>
  </village>
  <village>
    <villageId>64000080030</villageId>
    <villageName>林中里</villageName>
  </village>
  <village>
    <villageId>64000080031</villageId>
    <villageName>林泉里</villageName>
  </village>
  <village>
    <villageId>64000080032</villageId>
    <villageName>林南里</villageName>
  </village>
  <village>
    <villageId>64000080033</villageId>
    <villageName>中正里</villageName>
  </village>
  <village>
    <villageId>64000080034</villageId>
    <villageName>尚義里</villageName>
  </village>
  <village>
    <villageId>64000080035</villageId>
    <villageName>同慶里</villageName>
  </village>
  <village>
    <villageId>64000080036</villageId>
    <villageName>凱旋里</villageName>
  </village>
  <village>
    <villageId>64000080037</villageId>
    <villageName>安祥里</villageName>
  </village>
  <village>
    <villageId>64000080038</villageId>
    <villageName>奏捷里</villageName>
  </village>
  <village>
    <villageId>64000080039</villageId>
    <villageName>福壽里</villageName>
  </village>
  <village>
    <villageId>64000080040</villageId>
    <villageName>福南里</villageName>
  </village>
  <village>
    <villageId>64000080041</villageId>
    <villageName>五權里</villageName>
  </village>
  <village>
    <villageId>64000080042</villageId>
    <villageName>民主里</villageName>
  </village>
  <village>
    <villageId>64000080043</villageId>
    <villageName>林德里</villageName>
  </village>
  <village>
    <villageId>64000080044</villageId>
    <villageName>林貴里</villageName>
  </village>
  <village>
    <villageId>64000080045</villageId>
    <villageName>林榮里</villageName>
  </village>
  <village>
    <villageId>64000080046</villageId>
    <villageName>英明里</villageName>
  </village>
  <village>
    <villageId>64000080047</villageId>
    <villageName>林靖里</villageName>
  </village>
  <village>
    <villageId>64000080048</villageId>
    <villageName>朝陽里</villageName>
  </village>
  <village>
    <villageId>64000080049</villageId>
    <villageName>福隆里</villageName>
  </village>
  <village>
    <villageId>64000080050</villageId>
    <villageName>福祥里</villageName>
  </village>
  <village>
    <villageId>64000080051</villageId>
    <villageName>福海里</villageName>
  </village>
  <village>
    <villageId>64000080052</villageId>
    <villageName>福康里</villageName>
  </village>
  <village>
    <villageId>64000080053</villageId>
    <villageName>福人里</villageName>
  </village>
  <village>
    <villageId>64000080054</villageId>
    <villageName>福地里</villageName>
  </village>
  <village>
    <villageId>64000080055</villageId>
    <villageName>福居里</villageName>
  </village>
  <village>
    <villageId>64000080056</villageId>
    <villageName>福東里</villageName>
  </village>
  <village>
    <villageId>64000080057</villageId>
    <villageName>福西里</villageName>
  </village>
  <village>
    <villageId>64000080058</villageId>
    <villageName>永康里</villageName>
  </village>
  <village>
    <villageId>64000080059</villageId>
    <villageName>正文里</villageName>
  </village>
  <village>
    <villageId>64000080060</villageId>
    <villageName>正言里</villageName>
  </village>
  <village>
    <villageId>64000080061</villageId>
    <villageName>正大里</villageName>
  </village>
  <village>
    <villageId>64000080062</villageId>
    <villageName>五福里</villageName>
  </village>
  <village>
    <villageId>64000080063</villageId>
    <villageName>正心里</villageName>
  </village>
  <village>
    <villageId>64000080064</villageId>
    <villageName>正道里</villageName>
  </village>
  <village>
    <villageId>64000080065</villageId>
    <villageName>正義里</villageName>
  </village>
  <village>
    <villageId>64000080066</villageId>
    <villageName>正仁里</villageName>
  </village>
  <village>
    <villageId>64000080067</villageId>
    <villageName>文昌里</villageName>
  </village>
  <village>
    <villageId>64000080068</villageId>
    <villageName>建軍里</villageName>
  </village>
  <village>
    <villageId>64000080069</villageId>
    <villageName>衛武里</villageName>
  </village>
  <village>
    <villageId>64000080S01</villageId>
    <villageName/>
  </village>
</villages>
